{
  "processId": "27340d1a-21ae-4788-a3c1-42e4a3616e26",
  "message": {
    "Optimization Error": [
      "Solve result: infeasible. No solution is available!!",
      "Condition01 violated!!",
      "Condition041 violated!!",
      "Condition06 violated!!",
      "condition22 violated!!",
      "condition23 violated!!",
      "condition23a violated!!",
      "condition23b violated!!",
      "condition24 violated!!",
      "condition24a violated!!",
      "condition25 violated!!",
      "condition27 violated!!",
      "Constr8 violated!!",
      "Constr11 violated!!",
      "Constr12a1 violated!!",
      "Condition112a violated!!",
      "Condition112b violated!!",
      "Condition112c1 violated!!",
      "Condition112c2 violated!!",
      "Condition112c3 violated!!",
      "Condition112a1 violated!!",
      "Condition112a2 violated!!",
      "Condition112b1 violated!!",
      "Condition112b2 violated!!",
      "Condition113d1 violated!!",
      "Condition113d2 violated!!",
      "Condition113d3 violated!!",
      "Condition114a2 violated!!",
      "Condition114a3 violated!!",
      "Condition114e1 violated!!",
      "Condition114e2 violated!!",
      "Condition114e3 violated!!",
      "Condition114e6 violated!!",
      "Condition114f1 violated!!",
      "Condition114g1 violated!!",
      "Constr17a violated!!",
      "Constr13c1 violated!!",
      "Constr13c2 violated!!",
      "Constr13 violated!!",
      "Constr15b1 violated!!",
      "Constr15b2 violated!!",
      "Constr15c1 violated!!",
      "Constr15c2 violated!!",
      "Constr153 violated!!",
      "Constr154 violated!!",
      "Constr16b1 violated!!",
      "Constr16b2 violated!!",
      "Constr161 violated!!",
      "Constr163 violated!!",
      "Constr164 violated!!",
      "Constr16a violated!!",
      "Constr16b violated!!",
      "Constr18a violated!!",
      "Constr18b violated!!",
      "Constr19a violated!!",
      "Constr19b violated!!",
      "Constr18d violated!!",
      "Condition200a violated!!",
      "Condition20a violated!!",
      "Condition20b violated!!",
      "Condition20c violated!!",
      "Condition21a violated!!",
      "Condition21b violated!!",
      "Condition21c violated!!"
    ]
  },
  "errors": [
    {
      "errorHeading": "Optimization Error",
      "errorDetails": [
        "Solve result: infeasible. No solution is available!!",
        "Condition01 violated!!",
        "Condition041 violated!!",
        "Condition06 violated!!",
        "condition22 violated!!",
        "condition23 violated!!",
        "condition23a violated!!",
        "condition23b violated!!",
        "condition24 violated!!",
        "condition24a violated!!",
        "condition25 violated!!",
        "condition27 violated!!",
        "Constr8 violated!!",
        "Constr11 violated!!",
        "Constr12a1 violated!!",
        "Condition112a violated!!",
        "Condition112b violated!!",
        "Condition112c1 violated!!",
        "Condition112c2 violated!!",
        "Condition112c3 violated!!",
        "Condition112a1 violated!!",
        "Condition112a2 violated!!",
        "Condition112b1 violated!!",
        "Condition112b2 violated!!",
        "Condition113d1 violated!!",
        "Condition113d2 violated!!",
        "Condition113d3 violated!!",
        "Condition114a2 violated!!",
        "Condition114a3 violated!!",
        "Condition114e1 violated!!",
        "Condition114e2 violated!!",
        "Condition114e3 violated!!",
        "Condition114e6 violated!!",
        "Condition114f1 violated!!",
        "Condition114g1 violated!!",
        "Constr17a violated!!",
        "Constr13c1 violated!!",
        "Constr13c2 violated!!",
        "Constr13 violated!!",
        "Constr15b1 violated!!",
        "Constr15b2 violated!!",
        "Constr15c1 violated!!",
        "Constr15c2 violated!!",
        "Constr153 violated!!",
        "Constr154 violated!!",
        "Constr16b1 violated!!",
        "Constr16b2 violated!!",
        "Constr161 violated!!",
        "Constr163 violated!!",
        "Constr164 violated!!",
        "Constr16a violated!!",
        "Constr16b violated!!",
        "Constr18a violated!!",
        "Constr18b violated!!",
        "Constr19a violated!!",
        "Constr19b violated!!",
        "Constr18d violated!!",
        "Condition200a violated!!",
        "Condition20a violated!!",
        "Condition20b violated!!",
        "Condition20c violated!!",
        "Condition21a violated!!",
        "Condition21b violated!!",
        "Condition21c violated!!"
      ]
    }
  ],
  "hasLoadicator": true
}